ws_mcp/__init__.py
ws_mcp-0.1.11.dist-info/METADATA
ws_mcp-0.1.11.dist-info/WHEEL
ws_mcp-0.1.11.dist-info/entry_points.txt
ws_mcp-0.1.11.dist-info/RECORD
