Metadata-Version: 2.4
Name: ws-mcp
Version: 0.1.11
Summary: Wrap MCP servers with a WebSocket.
Project-URL: GitHub, https://github.com/nick1udwig/ws-mcp
Author-email: nick1udwig <hosted-fornet@protonmail.com>
Requires-Python: >=3.12
Requires-Dist: colorama>=0.4.6
Requires-Dist: jsonschema>=4.23.0
Requires-Dist: websockets>=14.1
